pitchai_agents/__init__.py
pitchai_agents/agent.py
pitchai_agents/agents/code_read_agent.py
pitchai_agents/agents/codebase_answer_agent.py
pitchai_agents/agents/colleagues.py
pitchai_agents/agents/dev_agent.py
pitchai_agents/agents/infra_new_agent.py
pitchai_agents/agents/mail_agent.py
pitchai_agents/agents/manager.py
pitchai_agents/agents/mng_agent.py
pitchai_agents/agents/simple_dev_agent.py
pitchai_agents/agents/tech_lead.py
pitchai_agents/agents/webagent.py
pitchai_agents/agents/webagent_new.py
pitchai_agents/async_partial.py
pitchai_agents/completion.py
pitchai_agents/dev_loop.py
pitchai_agents/discord_listen.py
pitchai_agents/dynamic_unittest.py
pitchai_agents/evolution_loop.py
pitchai_agents/history.py
pitchai_agents/iter.py
pitchai_agents/log_feedback.py
pitchai_agents/logs/reports/Jennifer_Garcia_277.md
pitchai_agents/logs/reports/Jody_Sanchez_978.md
pitchai_agents/logs/reports/Matthew_Snyder_694.md
pitchai_agents/logs/reports/Melissa_Gould_915.md
pitchai_agents/logs/reports/Michael_Martin_832.md
pitchai_agents/logs/reports/Stephanie_Hawkins_285.md
pitchai_agents/logs/reports/William_Ortiz_364.md
pitchai_agents/max_step.py
pitchai_agents/questions/codebase_followup_subquestions.py
pitchai_agents/remarks/remarks.md
pitchai_agents/report/code_agent_report.md
pitchai_agents/report/current_report.md
pitchai_agents/report/integrate_text.py
pitchai_agents/report/md_headers.py
pitchai_agents/report/relevant_headers.py
pitchai_agents/report/update_report.py
pitchai_agents/summarizations/summarized_history.md
pitchai_agents/tools/__init__.py
pitchai_agents/tools/communicate.py
pitchai_agents/tools/discord.py
pitchai_agents/tools/main.py
pitchai_agents/tools/read.py
pitchai_agents/tools/web.py
pitchai_agents/utils.py
pitchai_agents-0.1.0.dist-info/METADATA
pitchai_agents-0.1.0.dist-info/WHEEL
pitchai_agents-0.1.0.dist-info/RECORD
