Metadata-Version: 2.3
Name: pitchai_agents
Version: 0.1.0
Summary: 
Author: PitchAI
Author-email: info@pitchai.net
Requires-Python: >3.9.0,<3.13
Classifier: Programming Language :: Python :: 3
Classifier: Programming Language :: Python :: 3.10
Classifier: Programming Language :: Python :: 3.11
Classifier: Programming Language :: Python :: 3.12
Requires-Dist: aioprocessing (>=2.0.1,<3.0.0)
Requires-Dist: authlib (>=1.4.1,<2.0.0)
Requires-Dist: bs4 (>=0.0.2,<0.0.3)
Requires-Dist: datasets (==2.20)
Requires-Dist: discord-py (>=2.5.2,<3.0.0)
Requires-Dist: docker (>=7.1.0,<8.0.0)
Requires-Dist: evaluate (>=0.4.3,<0.5.0)
Requires-Dist: faker (>=37.0.0,<38.0.0)
Requires-Dist: fuzzywuzzy (>=0.18.0,<0.19.0)
Requires-Dist: git-python (>=1.0.3,<2.0.0)
Requires-Dist: google (>=3.0.0,<4.0.0)
Requires-Dist: googleapis-common-protos (>=1.67.0,<2.0.0)
Requires-Dist: grpcio (>=1.48.1)
Requires-Dist: grpcio-status (>=1.70.0,<2.0.0)
Requires-Dist: gunicorn (>=23.0.0,<24.0.0)
Requires-Dist: httpx (==0.27.2)
Requires-Dist: huggingface-hub (==0.24.1)
Requires-Dist: itsdangerous (>=2.2.0,<3.0.0)
Requires-Dist: jinja2 (>=3.1.4,<4.0.0)
Requires-Dist: mako (>=1.3.6,<2.0.0)
Requires-Dist: markdown (>=3.6,<4.0)
Requires-Dist: markdown-analysis (>=0.1.3,<0.2.0)
Requires-Dist: markdownify (>=1.0.0,<2.0.0)
Requires-Dist: markitdown (>=0.0.1a4,<0.0.2)
Requires-Dist: meilisearch (==0.32.0)
Requires-Dist: meilisearch-python-sdk (==4.0.0)
Requires-Dist: numpy (<2)
Requires-Dist: oauthlib (>=3.2.2,<4.0.0)
Requires-Dist: openai (==1.35.10)
Requires-Dist: openpyxl (>=3.1.5,<4.0.0)
Requires-Dist: opentelemetry-api (>=1.30.0,<2.0.0)
Requires-Dist: opentelemetry-exporter-otlp (>=1.30.0,<2.0.0)
Requires-Dist: opentelemetry-instrumentation-fastapi (>=0.51b0,<0.52)
Requires-Dist: opentelemetry-instrumentation-logging (>=0.51b0,<0.52)
Requires-Dist: opentelemetry-instrumentation-requests (>=0.51b0,<0.52)
Requires-Dist: opentelemetry-sdk (>=1.30.0,<2.0.0)
Requires-Dist: pandas (>=2.2.2,<3.0.0)
Requires-Dist: paramiko (>=3.5.0,<4.0.0)
Requires-Dist: pathvalidate (>=3.2.3,<4.0.0)
Requires-Dist: playwright (>=1.49.1,<2.0.0)
Requires-Dist: protobuf (>=5.29.3,<6.0.0)
Requires-Dist: psutil (>=7.0.0,<8.0.0)
Requires-Dist: psycopg2-binary (>=2.9.10,<3.0.0)
Requires-Dist: pyarrow (>=19.0.0,<20.0.0)
Requires-Dist: pympler (>=1.1,<2.0)
Requires-Dist: pyspark (==3.4.0)
Requires-Dist: pytest (>=8.3.4,<9.0.0)
Requires-Dist: pytest-asyncio (>=0.25.1,<0.26.0)
Requires-Dist: python-dotenv (>=1.0.1,<2.0.0)
Requires-Dist: python-logging-loki (>=0.3.1,<0.4.0)
Requires-Dist: python-multipart (>=0.0.9,<0.0.10)
Requires-Dist: pyyaml (>=6.0.2,<7.0.0)
Requires-Dist: rapidfuzz (>=3.11.0,<4.0.0)
Requires-Dist: rich (>=13.9.4,<14.0.0)
Requires-Dist: scikit-learn (>=1.6.0,<2.0.0)
Requires-Dist: serpapi (>=0.1.5,<0.2.0)
Requires-Dist: setuptools (>=75.6.0,<76.0.0)
Requires-Dist: sqlmodel (>=0.0.22,<0.0.23)
Requires-Dist: tabulate (>=0.9.0,<0.10.0)
Requires-Dist: tiktoken (>=0.9.0,<0.10.0)
Requires-Dist: tqdm (>=4.66.4,<5.0.0)
Requires-Dist: transformers (>4.20.0)
Requires-Dist: uvicorn (>=0.30.1,<0.31.0)
